{
  "codeName" : "original",
  "dERType" : "DER1N",
  "dynaModelFilePath" : "PSMODULES/base/PSDATAENTITIES/ir_attachment/PSDERS/DER1N_IR_ATTACHMENT_IR_ATTACHMENT_ORIGINAL_ID.json",
  "fKeyName" : "F8A20008362BC6DBA6",
  "getMajorPSDataEntity" : {
    "modelref" : true,
    "path" : "PSMODULES/base/PSDATAENTITIES/ir_attachment.json"
  },
  "masterOrder" : -1,
  "masterRS" : 0,
  "getMinorPSDataEntity" : {
    "modelref" : true,
    "path" : "PSMODULES/base/PSDATAENTITIES/ir_attachment.json"
  },
  "name" : "DER1N_IR_ATTACHMENT_IR_ATTACHMENT_ORIGINAL_ID",
  "orderValue" : 100,
  "getPSPickupDEField" : {
    "name" : "ORIGINAL_ID",
    "codeName" : "original_id"
  },
  "pickupDEFName" : "ORIGINAL_ID",
  "removeActionType" : 2,
  "removeOrder" : 0,
  "serviceCodeName" : "original",
  "enableFKey" : true
}