{
  "codeName" : "hr_applicant",
  "dERType" : "DER1N",
  "dynaModelFilePath" : "PSMODULES/hr/PSDATAENTITIES/hr_interview_feedback/PSDERS/DER1N_HR_INTERVIEW_FEEDBACK_HR_APPLICANT_APPLICANT_ID.json",
  "fKeyName" : "FBBD5AB2B58F2E9925",
  "logicName" : "候选人申请",
  "getMajorPSDataEntity" : {
    "modelref" : true,
    "path" : "PSMODULES/hr/PSDATAENTITIES/hr_applicant.json"
  },
  "masterOrder" : -1,
  "masterRS" : 0,
  "minorCodeName" : "hr_interview_feedbacks",
  "getMinorPSDataEntity" : {
    "modelref" : true,
    "path" : "PSMODULES/hr/PSDATAENTITIES/hr_interview_feedback.json"
  },
  "minorServiceCodeName" : "hr_interview_feedbacks",
  "name" : "DER1N_HR_INTERVIEW_FEEDBACK_HR_APPLICANT_APPLICANT_ID",
  "orderValue" : 100,
  "getPSPickupDEField" : {
    "name" : "APPLICANT_ID",
    "codeName" : "applicant_id"
  },
  "pickupDEFName" : "APPLICANT_ID",
  "removeActionType" : -1,
  "removeOrder" : 0,
  "serviceCodeName" : "hr_applicant",
  "enableFKey" : true
}